mavtel_client/__init__.py
mavtel_client/_generate.py
mavtel_client/client/__init__.py
mavtel_client/client/base.py
mavtel_client/client/client.py
mavtel_client/client/mixins/__init__.py
mavtel_client/client/mixins/metrics_mixin.py
mavtel_client/client/mixins/services_mixin.py
mavtel_client-0.0.6.data/data/docs/README.md
mavtel_client-0.0.6.data/data/version/.BUILD
mavtel_client-0.0.6.data/data/version/.VERSION
mavtel_models/__init__.py
mavtel_models/supported_metrics.py
mavtel_models/api/__init__.py
mavtel_models/api/api_info.py
mavtel_models/api/app_ready_response.py
mavtel_models/api/collector_state.py
mavtel_models/api/session_state.py
mavtel_models/api/storage_state.py
mavtel_models/mavlink/__init__.py
mavtel_models/mavlink/base_metric_model.py
mavtel_models/mavlink/metrics/__init__.py
mavtel_models/mavlink/metrics/actuator_control_target.py
mavtel_models/mavlink/metrics/actuator_output_status.py
mavtel_models/mavlink/metrics/armed.py
mavtel_models/mavlink/metrics/attitude_angular_velocity_body.py
mavtel_models/mavlink/metrics/attitude_euler.py
mavtel_models/mavlink/metrics/attitude_quaternion.py
mavtel_models/mavlink/metrics/battery.py
mavtel_models/mavlink/metrics/camera_attitude_euler.py
mavtel_models/mavlink/metrics/camera_attitude_quaternion.py
mavtel_models/mavlink/metrics/distance_sensor.py
mavtel_models/mavlink/metrics/fixedwing_metrics.py
mavtel_models/mavlink/metrics/flight_mode.py
mavtel_models/mavlink/metrics/gps_info.py
mavtel_models/mavlink/metrics/ground_truth.py
mavtel_models/mavlink/metrics/heading.py
mavtel_models/mavlink/metrics/health.py
mavtel_models/mavlink/metrics/health_all_ok.py
mavtel_models/mavlink/metrics/home.py
mavtel_models/mavlink/metrics/imu.py
mavtel_models/mavlink/metrics/in_air.py
mavtel_models/mavlink/metrics/landed_state.py
mavtel_models/mavlink/metrics/odometry.py
mavtel_models/mavlink/metrics/position.py
mavtel_models/mavlink/metrics/position_velocity_ned.py
mavtel_models/mavlink/metrics/raw_gps.py
mavtel_client-0.0.6.dist-info/METADATA
mavtel_client-0.0.6.dist-info/WHEEL
mavtel_client-0.0.6.dist-info/top_level.txt
mavtel_client-0.0.6.dist-info/RECORD
